gitgulf/main.py
gitgulf/repository.py
gitgulf/repository_manager.py
gitgulf/table.py
gitgulf-0.1.0.dist-info/LICENSE
gitgulf-0.1.0.dist-info/METADATA
gitgulf-0.1.0.dist-info/WHEEL
gitgulf-0.1.0.dist-info/entry_points.txt
gitgulf-0.1.0.dist-info/RECORD
