Metadata-Version: 2.1
Name: gitgulf
Version: 0.1.0
Summary: A CLI tool for managing multiple Git repositories collectively.
Home-page: https://github.com/tychop/gitgulf
License: MIT
Author: Tycho Pandelaar
Author-email: tychop@me.com
Requires-Python: >=3.6,<4.0
Classifier: License :: OSI Approved :: MIT License
Classifier: Operating System :: OS Independent
Classifier: Programming Language :: Python :: 3
Classifier: Programming Language :: Python :: 3.6
Classifier: Programming Language :: Python :: 3.7
Classifier: Programming Language :: Python :: 3.8
Classifier: Programming Language :: Python :: 3.9
Classifier: Programming Language :: Python :: 3.10
Classifier: Programming Language :: Python :: 3.11
Classifier: Programming Language :: Python :: 3.12
